django_smarty-0.1.3.dist-info/DESCRIPTION.rst
django_smarty-0.1.3.dist-info/METADATA
django_smarty-0.1.3.dist-info/RECORD
django_smarty-0.1.3.dist-info/WHEEL
django_smarty-0.1.3.dist-info/metadata.json
django_smarty-0.1.3.dist-info/top_level.txt
smarty/__init__.py
smarty/settings.py
smarty/templatetags/__init__.py
smarty/templatetags/smarty_tags.py
smarty/utils/__init__.py
smarty/utils/smarty.py
